stlock/__init__.py
stlock/stlock.py
stlock-0.0.10.dist-info/METADATA
stlock-0.0.10.dist-info/WHEEL
stlock-0.0.10.dist-info/top_level.txt
stlock-0.0.10.dist-info/RECORD
