Metadata-Version: 2.1
Name: stlock
Version: 0.0.10
Summary: Python auth lib for https://iam.stlcode.ru service
Author: Smart Techno Lab
Author-email: office@stl.im
Classifier: Programming Language :: Python :: 3.6
Classifier: Programming Language :: Python :: 3.7
Classifier: Programming Language :: Python :: 3.8
Classifier: Programming Language :: Python :: 3.9
Classifier: Programming Language :: Python :: 3.10
Classifier: Programming Language :: Python :: 3.11
Classifier: Programming Language :: Python :: 3.12
Classifier: Development Status :: 3 - Alpha
Requires-Dist: requests
Requires-Dist: pyjwt
